{
  "slug": "ac-macau",
  "name": "AC．",
  "city": "Macau",
  "country": "Macao SAR China",
  "placeId": "ChIJ88g14uB6ATQR9qyFtCzje8Y",
  "googleName": "Macao",
  "formattedAddress": "Macao",
  "phone": null,
  "website": null,
  "googleMapsUrl": "https://maps.google.com/?cid=14302274822791867638",
  "rating": null,
  "reviewCount": null,
  "coords": [
    22.198745,
    113.543873
  ],
  "openingHours": null,
  "editorialSummary": null,
  "photoUrls": [
    "https://nvdnfrvzx5yfyxil.private.blob.vercel-storage.com/bakery-photos/ac-macau/0.jpg"
  ],
  "enrichedAt": "2026-04-29T09:10:38.233Z"
}