{
  "slug": "agencia-la-bendicion-el-leon-dorado-chinandega",
  "name": "Agencia La Bendición El León Dorado",
  "city": "Chinandega",
  "country": "Nicaragua",
  "placeId": "ChIJsbeV8avxcI8RaAi6m93rahU",
  "googleName": "Agencia La Bendicion El Leon Dorado",
  "formattedAddress": "JVG9+GV5, Chinandega, Nicaragua",
  "phone": null,
  "website": null,
  "googleMapsUrl": "https://maps.google.com/?cid=1543305159360776296",
  "rating": null,
  "reviewCount": null,
  "coords": [
    12.6262539,
    -87.1303521
  ],
  "openingHours": null,
  "editorialSummary": null,
  "photoUrls": [],
  "enrichedAt": "2026-04-29T09:37:56.074Z"
}