{
  "slug": "alkafrawi-food-co-hebron",
  "name": "Alkafrawi FOOD CO.",
  "city": "Hebron",
  "country": "Palestine",
  "placeId": "ChIJRboO6qHmAhURP70FW7nzmEA",
  "googleName": "شركه الكفراوي للمواد الغذائيه kafrawi food co",
  "formattedAddress": "حارة الشيخ، الخليل",
  "phone": "02 222 2525",
  "website": "http://www.kafrawifood.com/",
  "googleMapsUrl": "https://maps.google.com/?cid=4654738192309009727",
  "rating": 4,
  "reviewCount": 67,
  "coords": [
    31.53190189999999,
    35.1050659
  ],
  "openingHours": [
    "Monday: 8:00 AM – 8:00 PM",
    "Tuesday: 8:00 AM – 8:00 PM",
    "Wednesday: 8:00 AM – 8:00 PM",
    "Thursday: 8:00 AM – 8:00 PM",
    "Friday: 8:00 – 11:30 AM",
    "Saturday: 8:00 AM – 8:00 PM",
    "Sunday: 8:00 AM – 8:00 PM"
  ],
  "editorialSummary": null,
  "photoUrls": [
    "https://dj278tuqr9qpj0lt.public.blob.vercel-storage.com/bakery-photos/alkafrawi-food-co-hebron/0.jpg"
  ],
  "enrichedAt": "2026-04-29T09:50:31.129Z"
}