{
  "slug": "baguette-absam",
  "name": "Baguette",
  "curatedName": "Baguette",
  "city": "Absam",
  "country": "Austria",
  "placeId": "ChIJP7Bfnn1vnUcRuQq9UGUVdqI",
  "googleName": "Baguette",
  "formattedAddress": "Dörferstraße 4, 6067 Absam, Austria",
  "phone": "050 3229 26075",
  "internationalPhone": "+43 50 3229 26075",
  "website": "https://www.mpreis.at/baguette-filialen/id-6075/baguette-absam/?utm_source=google&utm_medium=organic&utm_campaign=digitale_standorte",
  "googleMapsUrl": "https://maps.google.com/?cid=11706567806286629561",
  "rating": 4.1,
  "reviewCount": 223,
  "priceLevel": 2,
  "types": [
    "bakery",
    "establishment",
    "food",
    "point_of_interest",
    "store"
  ],
  "businessStatus": "OPERATIONAL",
  "coords": [
    47.294942,
    11.514206
  ],
  "openingHours": [
    "Monday: 7:30 AM – 7:00 PM",
    "Tuesday: 7:30 AM – 7:00 PM",
    "Wednesday: 7:30 AM – 7:00 PM",
    "Thursday: 7:30 AM – 7:00 PM",
    "Friday: 7:30 AM – 7:00 PM",
    "Saturday: 7:30 AM – 6:00 PM",
    "Sunday: Closed"
  ],
  "editorialSummary": null,
  "photoUrls": [
    "https://dj278tuqr9qpj0lt.public.blob.vercel-storage.com/bakery-photos/baguette-absam/0.jpg",
    "https://dj278tuqr9qpj0lt.public.blob.vercel-storage.com/bakery-photos/baguette-absam/1.jpg",
    "https://dj278tuqr9qpj0lt.public.blob.vercel-storage.com/bakery-photos/baguette-absam/2.jpg",
    "https://dj278tuqr9qpj0lt.public.blob.vercel-storage.com/bakery-photos/baguette-absam/3.jpg",
    "https://dj278tuqr9qpj0lt.public.blob.vercel-storage.com/bakery-photos/baguette-absam/4.jpg"
  ],
  "enrichedAt": "2026-04-08T11:15:59.449Z"
}