{
  "slug": "beedessee-s-pastry-bakery-bramsthan",
  "name": "Beedessee's Pastry & Bakery",
  "city": "Bramsthan",
  "country": "Mauritius",
  "placeId": "ChIJ_W1m6jbxfCER33EYOrW0MQk",
  "googleName": "Beedessee's Pastry & Bakery",
  "formattedAddress": "Bramsthan, Bramsthan village, Albatros lane, Mauritius",
  "phone": "5716 8600",
  "website": null,
  "googleMapsUrl": "https://maps.google.com/?cid=662509310656934367",
  "rating": 5,
  "reviewCount": 1,
  "coords": [
    -20.2164282,
    57.74278249999999
  ],
  "openingHours": null,
  "editorialSummary": null,
  "photoUrls": [
    "https://nvdnfrvzx5yfyxil.private.blob.vercel-storage.com/bakery-photos/beedessee-s-pastry-bakery-bramsthan/0.jpg"
  ],
  "enrichedAt": "2026-04-29T09:18:48.643Z"
}