{
  "slug": "den-helt-rigtige-bager-kongens-lyngby",
  "name": "Den Helt Rigtige Bager",
  "curatedName": "Den Helt Rigtige Bager",
  "city": "Kongens Lyngby",
  "country": "Denmark",
  "placeId": "ChIJkYB06T5OUkYR4C3HmsrsBxk",
  "googleName": "Den Helt Rigtige Bager",
  "formattedAddress": "Gammel Bagsværdvej 64, 2800 Kongens Lyngby, Denmark",
  "phone": "45 88 88 20",
  "internationalPhone": "+45 45 88 88 20",
  "website": "https://www.denheltrigtigebager.dk/",
  "googleMapsUrl": "https://maps.google.com/?cid=1803670530709466592",
  "rating": 4.4,
  "reviewCount": 705,
  "priceLevel": 2,
  "types": [
    "bakery",
    "establishment",
    "food",
    "point_of_interest",
    "store"
  ],
  "businessStatus": "OPERATIONAL",
  "coords": [
    55.7659247,
    12.4878992
  ],
  "openingHours": [
    "Monday: 6:00 AM – 5:30 PM",
    "Tuesday: 6:00 AM – 5:30 PM",
    "Wednesday: 6:00 AM – 5:30 PM",
    "Thursday: 6:00 AM – 5:30 PM",
    "Friday: 6:00 AM – 5:30 PM",
    "Saturday: 6:00 AM – 4:00 PM",
    "Sunday: 6:00 AM – 4:00 PM"
  ],
  "editorialSummary": null,
  "photoUrls": [
    "https://dj278tuqr9qpj0lt.public.blob.vercel-storage.com/bakery-photos/den-helt-rigtige-bager-kongens-lyngby/0.jpg",
    "https://dj278tuqr9qpj0lt.public.blob.vercel-storage.com/bakery-photos/den-helt-rigtige-bager-kongens-lyngby/1.jpg",
    "https://dj278tuqr9qpj0lt.public.blob.vercel-storage.com/bakery-photos/den-helt-rigtige-bager-kongens-lyngby/2.jpg",
    "https://dj278tuqr9qpj0lt.public.blob.vercel-storage.com/bakery-photos/den-helt-rigtige-bager-kongens-lyngby/3.jpg",
    "https://dj278tuqr9qpj0lt.public.blob.vercel-storage.com/bakery-photos/den-helt-rigtige-bager-kongens-lyngby/4.jpg"
  ],
  "enrichedAt": "2026-04-08T11:09:24.284Z"
}