{
  "slug": "fabrica-de-empanadas-el-sabor-de-la-libertad-alto-hospicio",
  "name": "Fábrica de Empanadas El Sabor de la Libertad",
  "city": "Alto Hospicio",
  "country": "Chile",
  "placeId": "ChIJGexp8wIVUpERybLzisIh8ek",
  "googleName": "Fabrica De Empanadas El Sabor De La Libertad",
  "formattedAddress": "Av. los Álamos 3035, 1130000 Alto Hospicio, Tarapacá, Chile",
  "phone": "9 4665 1820",
  "website": null,
  "googleMapsUrl": "https://maps.google.com/?cid=16857291999663076041",
  "rating": 5,
  "reviewCount": 2,
  "coords": [
    -20.2673943,
    -70.10349690000001
  ],
  "openingHours": null,
  "editorialSummary": null,
  "photoUrls": [
    "https://nvdnfrvzx5yfyxil.private.blob.vercel-storage.com/bakery-photos/fabrica-de-empanadas-el-sabor-de-la-libertad-alto-hospicio/0.jpg"
  ],
  "enrichedAt": "2026-04-29T07:43:31.398Z"
}