{
  "slug": "grau-s-rolls-arequipa",
  "name": "Grau's Rolls",
  "city": "Arequipa",
  "country": "Peru",
  "placeId": "ChIJNeF9AQBLQpERNNnYM5tn6UA",
  "googleName": "Rodrigo's Rolls",
  "formattedAddress": "JF62+5HX, Av. Ejército, Cayma 04018, Peru",
  "phone": "974 475 566",
  "website": "http://rodrigosrolls.com/",
  "googleMapsUrl": "https://maps.google.com/?cid=4677383604288411956",
  "rating": 4,
  "reviewCount": 7,
  "coords": [
    -16.3895126,
    -71.5485078
  ],
  "openingHours": null,
  "editorialSummary": null,
  "photoUrls": [
    "https://dj278tuqr9qpj0lt.public.blob.vercel-storage.com/bakery-photos/grau-s-rolls-arequipa/0.jpg"
  ],
  "enrichedAt": "2026-04-29T09:56:33.699Z"
}