{
  "slug": "moeke-van-eigen-deeg-aalst",
  "name": "Moeke van eigen deeg",
  "city": "Aalst",
  "country": "Belgium",
  "placeId": "ChIJSTZVZg6Xw0cRNCjyoT7KIr8",
  "googleName": "Moeke van eigen deeg",
  "formattedAddress": "Jozef Borremanstraat 32, 9300 Aalst, Belgium",
  "phone": null,
  "website": "https://www.instagram.com/moekevaneigendeeg",
  "googleMapsUrl": "https://maps.google.com/?cid=13772792980806182964",
  "rating": 5,
  "reviewCount": 5,
  "coords": [
    50.9455739,
    4.060451899999999
  ],
  "openingHours": null,
  "editorialSummary": null,
  "photoUrls": [
    "https://nvdnfrvzx5yfyxil.private.blob.vercel-storage.com/bakery-photos/moeke-van-eigen-deeg-aalst/0.jpg"
  ],
  "enrichedAt": "2026-04-29T07:03:35.097Z"
}