{
  "slug": "padaria-di-nos-tarrafal",
  "name": "Padaria Di Nos",
  "city": "Tarrafal",
  "country": "Cape Verde",
  "placeId": "ChIJsYgUUQB1SgkRYiWh1t8XUsE",
  "googleName": "Padaria Di Nós",
  "formattedAddress": "76HX+65Q, Tarrafal, Cabo Verde",
  "phone": null,
  "website": null,
  "googleMapsUrl": "https://maps.google.com/?cid=13930222847556396386",
  "rating": 4,
  "reviewCount": 1,
  "coords": [
    15.27809,
    -23.7520052
  ],
  "openingHours": null,
  "editorialSummary": null,
  "photoUrls": [
    "https://dj278tuqr9qpj0lt.public.blob.vercel-storage.com/bakery-photos/padaria-di-nos-tarrafal/0.jpg"
  ],
  "enrichedAt": "2026-04-29T07:40:50.412Z"
}