{
  "slug": "panaderia-pradera-juarez",
  "name": "Panaderia Pradera",
  "curatedName": "Panaderia Pradera",
  "city": "Juárez",
  "country": "Mexico",
  "placeId": "ChIJSQv7ijhc54YR86ZONMoabaI",
  "googleName": "Panadería Pradera",
  "formattedAddress": "C. Rancho Agua Caliente 3105, Pradera Dorada, 32618 Juárez, Chih., Mexico",
  "phone": null,
  "internationalPhone": null,
  "website": null,
  "googleMapsUrl": "https://maps.google.com/?cid=11704040462369072883",
  "rating": 4.6,
  "reviewCount": 728,
  "priceLevel": 2,
  "types": [
    "bakery",
    "establishment",
    "food",
    "point_of_interest",
    "store"
  ],
  "businessStatus": "OPERATIONAL",
  "coords": [
    31.7013716,
    -106.4183448
  ],
  "openingHours": [
    "Monday: 6:30 AM – 10:00 PM",
    "Tuesday: 6:30 AM – 10:00 PM",
    "Wednesday: 6:30 AM – 10:00 PM",
    "Thursday: 6:30 AM – 10:00 PM",
    "Friday: 6:30 AM – 10:00 PM",
    "Saturday: 6:30 AM – 10:00 PM",
    "Sunday: 6:30 AM – 10:00 PM"
  ],
  "editorialSummary": null,
  "photoUrls": [
    "https://dj278tuqr9qpj0lt.public.blob.vercel-storage.com/bakery-photos/panaderia-pradera-juarez/0.jpg"
  ],
  "enrichedAt": "2026-04-29T04:44:47.889Z"
}