{
  "slug": "pastry-and-eatery-corner-abuja",
  "name": "Pastry and Eatery Corner",
  "city": "Abuja",
  "country": "Nigeria",
  "placeId": "ChIJtxxBO3oMThAR7HYY_W35ggQ",
  "googleName": "Pastry & Eatery Corner",
  "formattedAddress": "Plot 4 Ubiaja Cres, Garki 2, Abuja 900110, Federal Capital Territory, Nigeria",
  "phone": "0809 061 6327",
  "website": null,
  "googleMapsUrl": "https://maps.google.com/?cid=325096373917087468",
  "rating": 4.3,
  "reviewCount": 9,
  "coords": [
    9.018686899999999,
    7.4905282
  ],
  "openingHours": [
    "Monday: 8:00 AM – 6:00 PM",
    "Tuesday: 8:00 AM – 6:00 PM",
    "Wednesday: 8:00 AM – 6:00 PM",
    "Thursday: 8:00 AM – 6:00 PM",
    "Friday: 8:00 AM – 6:00 PM",
    "Saturday: 8:00 AM – 6:00 PM",
    "Sunday: Closed"
  ],
  "editorialSummary": null,
  "photoUrls": [
    "https://nvdnfrvzx5yfyxil.private.blob.vercel-storage.com/bakery-photos/pastry-and-eatery-corner-abuja/0.jpg"
  ],
  "enrichedAt": "2026-04-29T09:41:15.723Z"
}