{
  "slug": "pate-boulanger",
  "name": "Pate Boulanger",
  "city": "أربيل",
  "country": "Iraq",
  "placeId": "ChIJx7EuOQwjB0ARZeiy_TOtD2Y",
  "googleName": "MACCANNOLI- قاوەخانەی ماکانۆلی",
  "formattedAddress": "MNW TOWERS, 40 Gulan St, Erbil, Erbil Governorate, Iraq",
  "phone": "0751 818 2773",
  "website": null,
  "googleMapsUrl": "https://maps.google.com/?cid=7354287155330607205",
  "rating": 4.1,
  "reviewCount": 219,
  "coords": [
    36.2049217,
    43.9842033
  ],
  "openingHours": [
    "Monday: 7:00 AM – 12:00 AM",
    "Tuesday: 7:00 AM – 12:00 AM",
    "Wednesday: 7:00 AM – 12:00 AM",
    "Thursday: 7:00 AM – 12:00 AM",
    "Friday: 7:00 AM – 12:00 AM",
    "Saturday: 7:00 AM – 12:00 AM",
    "Sunday: 7:00 AM – 12:00 AM"
  ],
  "editorialSummary": null,
  "photoUrls": [
    "https://nvdnfrvzx5yfyxil.private.blob.vercel-storage.com/bakery-photos/pate-boulanger/0.jpg"
  ],
  "enrichedAt": "2026-04-29T08:38:10.031Z"
}