{
  "slug": "queen-bee-bakery-quan-hai-an",
  "name": "Queen Bee Bakery",
  "curatedName": "Queen Bee Bakery",
  "city": "Quận Hải An",
  "country": "Vietnam",
  "placeId": "ChIJya_P2emtNTERc1TM4HUQa0k",
  "googleName": "Queen bee bakery",
  "formattedAddress": "44 P. Tân Mai, Tân Mai, Hoàng Mai, Hà Nội, Vietnam",
  "phone": "0912 880 564",
  "internationalPhone": "+84 912 880 564",
  "website": "https://www.facebook.com/share/1D6BrEpF3a/?mibextid=wwXIfr",
  "googleMapsUrl": "https://maps.google.com/?cid=5290340285745484915",
  "rating": 4.6,
  "reviewCount": 9,
  "priceLevel": null,
  "types": [
    "bakery",
    "establishment",
    "food",
    "point_of_interest",
    "store"
  ],
  "businessStatus": "OPERATIONAL",
  "coords": [
    20.9835016,
    105.8473955
  ],
  "openingHours": [
    "Monday: 7:00 AM – 10:30 PM",
    "Tuesday: 7:00 AM – 10:30 PM",
    "Wednesday: 7:00 AM – 10:30 PM",
    "Thursday: 7:00 AM – 10:30 PM",
    "Friday: 7:00 AM – 10:30 PM",
    "Saturday: 7:00 AM – 10:30 PM",
    "Sunday: 7:00 AM – 10:30 PM"
  ],
  "editorialSummary": null,
  "photoUrls": [
    "https://nvdnfrvzx5yfyxil.private.blob.vercel-storage.com/bakery-photos/queen-bee-bakery-quan-hai-an/0.jpg"
  ],
  "enrichedAt": "2026-04-29T05:19:42.006Z"
}