{
  "slug": "ro-patisserie-macau",
  "name": "Ro Patisserie",
  "city": "Macau",
  "country": "Macao SAR China",
  "placeId": "ChIJafmWAgB7ATQRIfUb088vDCE",
  "googleName": "Ro Patisserie",
  "formattedAddress": "60 DA號 R. da Barca, Macao",
  "phone": null,
  "website": null,
  "googleMapsUrl": "https://maps.google.com/?cid=2381330872618710305",
  "rating": null,
  "reviewCount": null,
  "coords": [
    22.2024268,
    113.5424409
  ],
  "openingHours": null,
  "editorialSummary": null,
  "photoUrls": [],
  "enrichedAt": "2026-04-29T09:10:02.562Z"
}