{
  "slug": "rumy-cochabamba",
  "name": "Rumy",
  "city": "Cochabamba",
  "country": "Bolivia",
  "placeId": "ChIJa3qFaZl045MRDYw-RnUBNe8",
  "googleName": "Rumy Mayu",
  "formattedAddress": "Rumy Mayu, Cochabamba, Bolivia",
  "phone": null,
  "website": null,
  "googleMapsUrl": "https://maps.google.com/?cid=17236684752031747085",
  "rating": 3.6,
  "reviewCount": 5,
  "coords": [
    -17.390035,
    -66.2080282
  ],
  "openingHours": null,
  "editorialSummary": null,
  "photoUrls": [
    "https://dj278tuqr9qpj0lt.public.blob.vercel-storage.com/bakery-photos/rumy-cochabamba/0.jpg"
  ],
  "enrichedAt": "2026-04-29T07:13:15.009Z"
}