{
  "slug": "safran-patisserie-chaguanas",
  "name": "Safran Patisserie",
  "city": "Chaguanas",
  "country": "Trinidad & Tobago",
  "placeId": "ChIJ0UnhJqn5NYwRQEV3WtuQpbE",
  "googleName": "Safran Patisserie",
  "formattedAddress": "4 Gaston St, Montrose, Trinidad and Tobago",
  "phone": "(868) 784-1499",
  "website": null,
  "googleMapsUrl": "https://maps.google.com/?cid=12800796787660506432",
  "rating": 4.5,
  "reviewCount": 80,
  "coords": [
    10.5174449,
    -61.4055232
  ],
  "openingHours": [
    "Monday: Closed",
    "Tuesday: 10:00 AM – 5:00 PM",
    "Wednesday: 10:00 AM – 5:00 PM",
    "Thursday: 10:00 AM – 5:00 PM",
    "Friday: 10:00 AM – 5:00 PM",
    "Saturday: 10:00 AM – 5:00 PM",
    "Sunday: Closed"
  ],
  "editorialSummary": null,
  "photoUrls": [
    "https://nvdnfrvzx5yfyxil.private.blob.vercel-storage.com/bakery-photos/safran-patisserie-chaguanas/0.jpg"
  ],
  "enrichedAt": "2026-04-29T10:43:08.955Z"
}