{
  "slug": "yundem-tas-firin-akova",
  "name": "Yundem Tas Firin",
  "city": "Akova",
  "country": "Cyprus",
  "placeId": "ChIJI2m0IClL3hQRZvmFryVeHS8",
  "googleName": "YUNDEM TAŞ FIRIN",
  "formattedAddress": "Lefkoşa-İskele Yolu, Akova 99690 Famagusta, Akova 5000",
  "phone": "0533 838 36 80",
  "website": "https://yundemtasfirin.tr.gg/",
  "googleMapsUrl": "https://maps.google.com/?cid=3394973210058815846",
  "rating": 4.9,
  "reviewCount": 12,
  "coords": [
    35.2618014,
    33.7781456
  ],
  "openingHours": [
    "Monday: 6:00 AM – 12:00 AM",
    "Tuesday: 6:00 AM – 12:00 AM",
    "Wednesday: 6:00 AM – 12:00 AM",
    "Thursday: 6:00 AM – 12:00 AM",
    "Friday: 6:00 AM – 12:00 AM",
    "Saturday: 6:00 AM – 12:00 AM",
    "Sunday: 6:00 AM – 12:00 AM"
  ],
  "editorialSummary": null,
  "photoUrls": [
    "https://dj278tuqr9qpj0lt.public.blob.vercel-storage.com/bakery-photos/yundem-tas-firin-akova/0.jpg"
  ],
  "enrichedAt": "2026-04-29T07:51:52.544Z"
}